docutils-stubs/METADATA.toml
docutils-stubs/__init__.pyi
docutils-stubs/__main__.pyi
docutils-stubs/core.pyi
docutils-stubs/examples.pyi
docutils-stubs/frontend.pyi
docutils-stubs/io.pyi
docutils-stubs/nodes.pyi
docutils-stubs/py.typed
docutils-stubs/statemachine.pyi
docutils-stubs/languages/__init__.pyi
docutils-stubs/languages/af.pyi
docutils-stubs/languages/ar.pyi
docutils-stubs/languages/ca.pyi
docutils-stubs/languages/cs.pyi
docutils-stubs/languages/da.pyi
docutils-stubs/languages/de.pyi
docutils-stubs/languages/en.pyi
docutils-stubs/languages/eo.pyi
docutils-stubs/languages/es.pyi
docutils-stubs/languages/fa.pyi
docutils-stubs/languages/fi.pyi
docutils-stubs/languages/fr.pyi
docutils-stubs/languages/gl.pyi
docutils-stubs/languages/he.pyi
docutils-stubs/languages/it.pyi
docutils-stubs/languages/ja.pyi
docutils-stubs/languages/ka.pyi
docutils-stubs/languages/ko.pyi
docutils-stubs/languages/lt.pyi
docutils-stubs/languages/lv.pyi
docutils-stubs/languages/nl.pyi
docutils-stubs/languages/pl.pyi
docutils-stubs/languages/pt_br.pyi
docutils-stubs/languages/ru.pyi
docutils-stubs/languages/sk.pyi
docutils-stubs/languages/sv.pyi
docutils-stubs/languages/uk.pyi
docutils-stubs/languages/zh_cn.pyi
docutils-stubs/languages/zh_tw.pyi
docutils-stubs/parsers/__init__.pyi
docutils-stubs/parsers/commonmark_wrapper.pyi
docutils-stubs/parsers/docutils_xml.pyi
docutils-stubs/parsers/null.pyi
docutils-stubs/parsers/recommonmark_wrapper.pyi
docutils-stubs/parsers/rst/__init__.pyi
docutils-stubs/parsers/rst/roles.pyi
docutils-stubs/parsers/rst/states.pyi
docutils-stubs/parsers/rst/tableparser.pyi
docutils-stubs/parsers/rst/directives/__init__.pyi
docutils-stubs/parsers/rst/directives/admonitions.pyi
docutils-stubs/parsers/rst/directives/body.pyi
docutils-stubs/parsers/rst/directives/html.pyi
docutils-stubs/parsers/rst/directives/images.pyi
docutils-stubs/parsers/rst/directives/misc.pyi
docutils-stubs/parsers/rst/directives/parts.pyi
docutils-stubs/parsers/rst/directives/references.pyi
types_docutils-0.22.0.20250914.dist-info/licenses/LICENSE
types_docutils-0.22.0.20250914.dist-info/METADATA
types_docutils-0.22.0.20250914.dist-info/WHEEL
types_docutils-0.22.0.20250914.dist-info/top_level.txt
types_docutils-0.22.0.20250914.dist-info/RECORD
